MANIFEST.in
README.rst
setup.cfg
setup.py
docs/HISTORY.txt
docs/INSTALL.txt
docs/LICENSE.GPL
docs/LICENSE.txt
seantis/__init__.py
seantis.dir.roadworks.egg-info/PKG-INFO
seantis.dir.roadworks.egg-info/SOURCES.txt
seantis.dir.roadworks.egg-info/dependency_links.txt
seantis.dir.roadworks.egg-info/entry_points.txt
seantis.dir.roadworks.egg-info/namespace_packages.txt
seantis.dir.roadworks.egg-info/not-zip-safe
seantis.dir.roadworks.egg-info/requires.txt
seantis.dir.roadworks.egg-info/top_level.txt
seantis/dir/__init__.py
seantis/dir/roadworks/__init__.py
seantis/dir/roadworks/configure.zcml
seantis/dir/roadworks/directory.py
seantis/dir/roadworks/item.py
seantis/dir/roadworks/sync.sh
seantis/dir/roadworks/testing.py
seantis/dir/roadworks/upgrades.py
seantis/dir/roadworks/images/construction-marker.png
seantis/dir/roadworks/locales/seantis.dir.roadworks.pot
seantis/dir/roadworks/locales/de/LC_MESSAGES/seantis.dir.roadworks.po
seantis/dir/roadworks/profiles/default/catalog.xml
seantis/dir/roadworks/profiles/default/metadata.xml
seantis/dir/roadworks/profiles/default/types.xml
seantis/dir/roadworks/profiles/default/types/seantis.dir.roadworks.directory.xml
seantis/dir/roadworks/profiles/default/types/seantis.dir.roadworks.item.xml
seantis/dir/roadworks/templates/directory.pt
seantis/dir/roadworks/templates/directorydetail.pt
seantis/dir/roadworks/templates/item.pt
seantis/dir/roadworks/tests/__init__.py
seantis/dir/roadworks/tests/test_item.py
seantis/dir/roadworks/tests/data/test.png