Metadata-Version: 1.1
Name: seantis.dir.roadworks
Version: 1.7.1
Summary: Directory of Roadworks
Home-page: https://github.com/seantis/seantis.dir.roadworks
Author: Seantis GmbH
Author-email: info@seantis.ch
License: GPL
Platform: UNKNOWN
Classifier: Framework :: Plone
Classifier: Programming Language :: Python
